{"type": "FeatureCollection", "id": "http://wikidata.org/entity/Q121418883", "name": "Q121418883", "features": [{"type": "Feature", "id": "http://fuzzy-sl.squirrel.link/data/cisite_51", "name": "Crvena Stiljena (Montenegro)", "dateprops": [], "properties": {"http://archaeoinformatics.link/ontology#certaintyDesc": ["findspot mentioned in a scientific paper"], "http://archaeoinformatics.link/ontology#certaintyLevel": ["http://archaeoinformatics.link/ontology#high"], "http://archaeoinformatics.link/ontology#hasReference": ["Morley & Woodward, 2011"], "http://archaeoinformatics.link/ontology#partOf": ["http://archaeoinformatics.link/ontology#CampanianIgnimbriteProject"], "http://archaeoinformatics.link/ontology#siteType": ["http://archaeoinformatics.link/ontology#ArchaeologicalSite"], "http://archaeoinformatics.link/ontology#spatialType": ["http://archaeoinformatics.link/ontology#Cave", "http://archaeoinformatics.link/ontology#ArchaeologicalSite"], "http://purl.org/dc/terms/creator": ["https://orcid.org/0000-0002-3246-3531", "https://orcid.org/0000-0003-1100-6494"], "http://purl.org/dc/terms/license": ["https://creativecommons.org/licenses/by/4.0/"], "http://purl.org/dc/terms/rightsHolder": ["https://orcid.org/0000-0002-3246-3531", "https://orcid.org/0000-0003-1100-6494"], "http://www.opengis.net/ont/geosparql#hasGeometry": ["http://fuzzy-sl.squirrel.link/data/cisite_51_geom"], "http://www.w3.org/1999/02/22-rdf-syntax-ns#type": ["http://archaeoinformatics.link/ontology#Site", "http://www.w3.org/ns/prov#Entity", "https://pleiades.stoa.org/places/vocab#Place"], "http://www.w3.org/2000/01/rdf-schema#comment": ["CI findspot related from literature"], "http://www.w3.org/2000/01/rdf-schema#label": ["Crvena Stiljena (Montenegro)"], "http://www.w3.org/2004/02/skos/core#closeMatch": ["http://openstreetmap.org/node/10879170567", "http://wikidata.org/entity/Q121418883"], "http://www.w3.org/2004/02/skos/core#prefLabel": ["Crvena Stiljena (Montenegro)"], "http://www.w3.org/2004/02/skos/core#scopeNote": ["CI findspot related from literature"], "http://www.w3.org/ns/prov#wasAttributedTo": ["http://orcid.org/0009-0008-2877-3204", "https://github.com/Research-Squirrel-Engineers/campanian-ignimbrite-geo/blob/main/py/CI.py"], "http://www.w3.org/ns/prov#wasDerivedFrom": ["https://github.com/Research-Squirrel-Engineers/campanian-ignimbrite-geo"], "http://www.w3.org/ns/prov#wasGeneratedBy": ["http://fuzzy-sl.squirrel.link/data/cisite_51_activity", "http://fuzzy-sl.squirrel.link/data/cisite_51_pyscript"]}, "geometry": {"type": "Point", "coordinates": [18.4815, 42.779], "crs": "4326"}}], "numberMatched": 1, "numberReturned": 1, "bbox": [18.4815, 42.779, 18.4815, 42.779], "crs": "http://www.opengis.net/def/crs/EPSG/0/4326"}