{"type": "FeatureCollection", "id": "http://wikidata.org/entity/Q1860399", "name": "Q1860399", "features": [{"type": "Feature", "id": "http://fuzzy-sl.squirrel.link/data/cisite_27", "name": "Sant\u2018 Agata dei due Golfi", "dateprops": [], "properties": {"http://archaeoinformatics.link/ontology#certaintyDesc": ["TODO"], "http://archaeoinformatics.link/ontology#certaintyLevel": ["http://archaeoinformatics.link/ontology#medium"], "http://archaeoinformatics.link/ontology#hasReference": ["Civetta et al., 1997"], "http://archaeoinformatics.link/ontology#partOf": ["http://archaeoinformatics.link/ontology#CampanianIgnimbriteProject"], "http://archaeoinformatics.link/ontology#siteType": ["http://archaeoinformatics.link/ontology#ArchaeologicalSite"], "http://archaeoinformatics.link/ontology#spatialType": ["http://archaeoinformatics.link/ontology#InhabitedPlace"], "http://purl.org/dc/terms/creator": ["https://orcid.org/0000-0002-3246-3531", "https://orcid.org/0000-0003-1100-6494"], "http://purl.org/dc/terms/license": ["https://creativecommons.org/licenses/by/4.0/"], "http://purl.org/dc/terms/rightsHolder": ["https://orcid.org/0000-0002-3246-3531", "https://orcid.org/0000-0003-1100-6494"], "http://www.opengis.net/ont/geosparql#hasGeometry": ["http://fuzzy-sl.squirrel.link/data/cisite_27_geom"], "http://www.w3.org/1999/02/22-rdf-syntax-ns#type": ["http://archaeoinformatics.link/ontology#Site", "http://www.w3.org/ns/prov#Entity", "https://pleiades.stoa.org/places/vocab#Place"], "http://www.w3.org/2000/01/rdf-schema#comment": ["CI findspot related from literature"], "http://www.w3.org/2000/01/rdf-schema#label": ["Sant\u2018 Agata dei due Golfi"], "http://www.w3.org/2004/02/skos/core#closeMatch": ["http://wikidata.org/entity/Q1860399", "http://openstreetmap.org/node/705576753"], "http://www.w3.org/2004/02/skos/core#prefLabel": ["Sant\u2018 Agata dei due Golfi"], "http://www.w3.org/2004/02/skos/core#scopeNote": ["CI findspot related from literature"], "http://www.w3.org/ns/prov#wasAttributedTo": ["http://orcid.org/0000-0002-3246-3531", "https://github.com/Research-Squirrel-Engineers/campanian-ignimbrite-geo/blob/main/py/CI.py"], "http://www.w3.org/ns/prov#wasDerivedFrom": ["https://github.com/Research-Squirrel-Engineers/campanian-ignimbrite-geo"], "http://www.w3.org/ns/prov#wasGeneratedBy": ["http://fuzzy-sl.squirrel.link/data/cisite_27_activity", "http://fuzzy-sl.squirrel.link/data/cisite_27_pyscript"]}, "geometry": {"type": "Point", "coordinates": [14.3733, 40.607], "crs": "4326"}}], "numberMatched": 1, "numberReturned": 1, "bbox": [14.3733, 40.607, 14.3733, 40.607], "crs": "http://www.opengis.net/def/crs/EPSG/0/4326"}