{"type": "FeatureCollection", "id": "http://openstreetmap.org/node/299298568", "name": "299298568", "features": [{"type": "Feature", "id": "http://fuzzy-sl.squirrel.link/data/cisite_47", "name": "Tenaghi Philippon (Greece)", "dateprops": [], "properties": {"http://archaeoinformatics.link/ontology#certaintyDesc": ["findspot mentioned in a scientific paper"], "http://archaeoinformatics.link/ontology#certaintyLevel": ["http://archaeoinformatics.link/ontology#low"], "http://archaeoinformatics.link/ontology#dubiousMatch": ["http://openstreetmap.org/node/299298568"], "http://archaeoinformatics.link/ontology#hasReference": ["Lowe et al., 2012", "Wulf et al., 2018"], "http://archaeoinformatics.link/ontology#partOf": ["http://archaeoinformatics.link/ontology#CampanianIgnimbriteProject"], "http://archaeoinformatics.link/ontology#siteType": ["http://archaeoinformatics.link/ontology#ArchaeologicalSite"], "http://archaeoinformatics.link/ontology#spatialType": ["http://archaeoinformatics.link/ontology#UnknownCategory"], "http://purl.org/dc/terms/creator": ["https://orcid.org/0000-0002-3246-3531", "https://orcid.org/0000-0003-1100-6494"], "http://purl.org/dc/terms/license": ["https://creativecommons.org/licenses/by/4.0/"], "http://purl.org/dc/terms/rightsHolder": ["https://orcid.org/0000-0002-3246-3531", "https://orcid.org/0000-0003-1100-6494"], "http://www.opengis.net/ont/geosparql#hasGeometry": ["http://fuzzy-sl.squirrel.link/data/cisite_47_geom"], "http://www.w3.org/1999/02/22-rdf-syntax-ns#type": ["http://archaeoinformatics.link/ontology#Site", "http://www.w3.org/ns/prov#Entity", "https://pleiades.stoa.org/places/vocab#Place"], "http://www.w3.org/2000/01/rdf-schema#comment": ["CI findspot related from literature"], "http://www.w3.org/2000/01/rdf-schema#label": ["Tenaghi Philippon (Greece)"], "http://www.w3.org/2004/02/skos/core#prefLabel": ["Tenaghi Philippon (Greece)"], "http://www.w3.org/2004/02/skos/core#scopeNote": ["CI findspot related from literature"], "http://www.w3.org/ns/prov#wasAttributedTo": ["http://orcid.org/0009-0008-2877-3204", "https://github.com/Research-Squirrel-Engineers/campanian-ignimbrite-geo/blob/main/py/CI.py"], "http://www.w3.org/ns/prov#wasDerivedFrom": ["https://github.com/Research-Squirrel-Engineers/campanian-ignimbrite-geo"], "http://www.w3.org/ns/prov#wasGeneratedBy": ["http://fuzzy-sl.squirrel.link/data/cisite_47_activity", "http://fuzzy-sl.squirrel.link/data/cisite_47_pyscript"]}, "geometry": {"type": "Point", "coordinates": [24.2274, 40.9794], "crs": "4326"}}], "numberMatched": 1, "numberReturned": 1, "bbox": [24.2274, 40.9794, 24.2274, 40.9794], "crs": "http://www.opengis.net/def/crs/EPSG/0/4326"}